<?xml version="1.0" encoding="UTF-8"?>
<ITRETURN:ITR xmlns:ITRETURN="http://incometaxindiaefiling.gov.in/main" xmlns:ITR4SFORM="http://incometaxindiaefiling.gov.in/ITR4S" xmlns:ITRForm="http://incometaxindiaefiling.gov.in/master" xmlns:xsi="http://www.w3.org/2001/XMLSchema-instance" >
<ITR4SFORM:ITR4S>
<ITRForm:CreationInfo>
<ITRForm:SWVersionNo>R1</ITRForm:SWVersionNo>
<ITRForm:SWCreatedBy>SW92201617</ITRForm:SWCreatedBy>
<ITRForm:XMLCreatedBy>SW92201617</ITRForm:XMLCreatedBy>
<ITRForm:XMLCreationDate>2017-03-20</ITRForm:XMLCreationDate>
<ITRForm:IntermediaryCity>Delhi</ITRForm:IntermediaryCity>
<ITRForm:Digest>QG6Lt/nQFPzZKx+XELfko7gU2Oa2PLld13mG6tEwRWE=</ITRForm:Digest>
</ITRForm:CreationInfo>
<ITRForm:Form_ITR4S>
<ITRForm:FormName>ITR-4S</ITRForm:FormName>
<ITRForm:Description>For Indl having Income From Presemptive Business</ITRForm:Description>
<ITRForm:AssessmentYear>2016</ITRForm:AssessmentYear>
<ITRForm:SchemaVer>Ver1.0</ITRForm:SchemaVer>
<ITRForm:FormVer>Ver1.0</ITRForm:FormVer>
</ITRForm:Form_ITR4S>
<ITRForm:PersonalInfo>
<ITRForm:AssesseeName>
<ITRForm:FirstName>UTPAL</ITRForm:FirstName>
<ITRForm:MiddleName/>
<ITRForm:SurNameOrOrgName>MONDAL</ITRForm:SurNameOrOrgName>
</ITRForm:AssesseeName>
<ITRForm:PAN>AOAPM7867B</ITRForm:PAN>
<ITRForm:Address>
<ITRForm:ResidenceNo>-</ITRForm:ResidenceNo>
<ITRForm:ResidenceName>VILL.+ P.O. - SONAPUKUR</ITRForm:ResidenceName>
<ITRForm:RoadOrStreet/>
<ITRForm:LocalityOrArea>HAROA</ITRForm:LocalityOrArea>
<ITRForm:CityOrTownOrDistrict>NORTH 24 PARGANA</ITRForm:CityOrTownOrDistrict>
<ITRForm:StateCode>32</ITRForm:StateCode>
<ITRForm:CountryCode>91</ITRForm:CountryCode>
<ITRForm:PinCode>743502</ITRForm:PinCode>
<ITRForm:MobileNo>9331201723</ITRForm:MobileNo>
<ITRForm:EmailAddress>mousumi.bcc@gmail.com</ITRForm:EmailAddress>
</ITRForm:Address>
<ITRForm:DOB>1981-05-10</ITRForm:DOB>
<ITRForm:Gender>M</ITRForm:Gender>
<ITRForm:Status>I</ITRForm:Status>
<ITRForm:AadhaarCardFlg>N</ITRForm:AadhaarCardFlg>
</ITRForm:PersonalInfo>
<ITRForm:FilingStatus>
<ITRForm:DesigOfficerWardorCircle/>
<ITRForm:ReturnFileSec>12</ITRForm:ReturnFileSec>
<ITRForm:ReturnType>O</ITRForm:ReturnType>
<ITRForm:ResidentialStatus>RES</ITRForm:ResidentialStatus>
<ITRForm:TaxStatus>NT</ITRForm:TaxStatus>
<ITRForm:PortugeseCC5A>N</ITRForm:PortugeseCC5A>
</ITRForm:FilingStatus>
<ITRForm:ITR4S_IncomeDeductions>
<ITRForm:IncomeFromBusinessProf>352297</ITRForm:IncomeFromBusinessProf>
<ITRForm:IncomeFromSal>0</ITRForm:IncomeFromSal>
<ITRForm:TotalIncomeOfHP>0</ITRForm:TotalIncomeOfHP>
<ITRForm:IncomeOthSrc>622</ITRForm:IncomeOthSrc>
<ITRForm:GrossTotIncome>352919</ITRForm:GrossTotIncome>
<ITRForm:UsrDeductUndChapVIA>
<ITRForm:Section80C>78091</ITRForm:Section80C>
<ITRForm:Section80CCC>0</ITRForm:Section80CCC>
<ITRForm:Section80CCDEmployeeOrSE>0</ITRForm:Section80CCDEmployeeOrSE>
<ITRForm:Section80CCDEmployer>0</ITRForm:Section80CCDEmployer>
<ITRForm:Section80CCD1B>0</ITRForm:Section80CCD1B>
<ITRForm:Section80D>4500</ITRForm:Section80D>
<ITRForm:Section80DD>0</ITRForm:Section80DD>
<ITRForm:Section80DDB>0</ITRForm:Section80DDB>
<ITRForm:Section80E>0</ITRForm:Section80E>
<ITRForm:Section80G>0</ITRForm:Section80G>
<ITRForm:Section80GG>0</ITRForm:Section80GG>
<ITRForm:Section80GGC>0</ITRForm:Section80GGC>
<ITRForm:Section80U>0</ITRForm:Section80U>
<ITRForm:Section80RRB>0</ITRForm:Section80RRB>
<ITRForm:Section80QQB>0</ITRForm:Section80QQB>
<ITRForm:Section80CCG>0</ITRForm:Section80CCG>
<ITRForm:Section80TTA>622</ITRForm:Section80TTA>
<ITRForm:TotalChapVIADeductions>83213</ITRForm:TotalChapVIADeductions>
</ITRForm:UsrDeductUndChapVIA>
<ITRForm:DeductUndChapVIA>
<ITRForm:Section80C>78091</ITRForm:Section80C>
<ITRForm:Section80CCC>0</ITRForm:Section80CCC>
<ITRForm:Section80CCDEmployeeOrSE>0</ITRForm:Section80CCDEmployeeOrSE>
<ITRForm:Section80CCDEmployer>0</ITRForm:Section80CCDEmployer>
<ITRForm:Section80CCD1B>0</ITRForm:Section80CCD1B>
<ITRForm:Section80D>4500</ITRForm:Section80D>
<ITRForm:Section80DD>0</ITRForm:Section80DD>
<ITRForm:Section80DDB>0</ITRForm:Section80DDB>
<ITRForm:Section80E>0</ITRForm:Section80E>
<ITRForm:Section80G>0</ITRForm:Section80G>
<ITRForm:Section80GG>0</ITRForm:Section80GG>
<ITRForm:Section80GGC>0</ITRForm:Section80GGC>
<ITRForm:Section80U>0</ITRForm:Section80U>
<ITRForm:Section80RRB>0</ITRForm:Section80RRB>
<ITRForm:Section80QQB>0</ITRForm:Section80QQB>
<ITRForm:Section80CCG>0</ITRForm:Section80CCG>
<ITRForm:Section80TTA>622</ITRForm:Section80TTA>
<ITRForm:TotalChapVIADeductions>83213</ITRForm:TotalChapVIADeductions>
</ITRForm:DeductUndChapVIA>
<ITRForm:TotalIncome>269710</ITRForm:TotalIncome>
</ITRForm:ITR4S_IncomeDeductions>
<ITRForm:ITR4S_TaxComputation>
<ITRForm:TotalTaxPayable>1971</ITRForm:TotalTaxPayable>
<ITRForm:Rebate87A>1971</ITRForm:Rebate87A>
<ITRForm:TaxPayableOnRebate>0</ITRForm:TaxPayableOnRebate>
<ITRForm:SurchargeOnAboveCrore>0</ITRForm:SurchargeOnAboveCrore>
<ITRForm:EducationCess>0</ITRForm:EducationCess>
<ITRForm:GrossTaxLiability>0</ITRForm:GrossTaxLiability>
<ITRForm:Section89>0</ITRForm:Section89>
<ITRForm:NetTaxLiability>0</ITRForm:NetTaxLiability>
<ITRForm:TotalIntrstPay>0</ITRForm:TotalIntrstPay>
<ITRForm:IntrstPay>
<ITRForm:IntrstPayUs234A>0</ITRForm:IntrstPayUs234A>
<ITRForm:IntrstPayUs234B>0</ITRForm:IntrstPayUs234B>
<ITRForm:IntrstPayUs234C>0</ITRForm:IntrstPayUs234C>
</ITRForm:IntrstPay>
<ITRForm:TotTaxPlusIntrstPay>0</ITRForm:TotTaxPlusIntrstPay>
</ITRForm:ITR4S_TaxComputation>
<ITRForm:TaxPaid>
<ITRForm:TaxesPaid>
<ITRForm:AdvanceTax>0</ITRForm:AdvanceTax>
<ITRForm:TDS>0</ITRForm:TDS>
<ITRForm:TCS>0</ITRForm:TCS>
<ITRForm:SelfAssessmentTax>0</ITRForm:SelfAssessmentTax>
<ITRForm:TotalTaxesPaid>0</ITRForm:TotalTaxesPaid>
</ITRForm:TaxesPaid>
<ITRForm:BalTaxPayable>0</ITRForm:BalTaxPayable>
</ITRForm:TaxPaid>
<ITRForm:Refund>
<ITRForm:RefundDue>0</ITRForm:RefundDue>
<ITRForm:BankAccountDtls>
<ITRForm:PriBankDetails>
<ITRForm:IFSCCode>ORBC0101235</ITRForm:IFSCCode>
<ITRForm:BankName>ORIENTAL BANK OF COMMERCE</ITRForm:BankName>
<ITRForm:BankAccountNo>12352191002338</ITRForm:BankAccountNo>
<ITRForm:BankAccountType>SAV</ITRForm:BankAccountType>
</ITRForm:PriBankDetails>
<ITRForm:AddtnlBankDetails>
<ITRForm:IFSCCode>ORBC0101235</ITRForm:IFSCCode>
<ITRForm:BankName>ORIENTAL BANK OF COMMERCE</ITRForm:BankName>
<ITRForm:BankAccountNo>12351131001066</ITRForm:BankAccountNo>
<ITRForm:BankAccountType>CUR</ITRForm:BankAccountType>
</ITRForm:AddtnlBankDetails>
<ITRForm:AddtnlBankDetails>
<ITRForm:IFSCCode>SBHY0021347</ITRForm:IFSCCode>
<ITRForm:BankName>STATE BANK OF HYDERABAD</ITRForm:BankName>
<ITRForm:BankAccountNo>62173350569</ITRForm:BankAccountNo>
<ITRForm:BankAccountType>SAV</ITRForm:BankAccountType>
</ITRForm:AddtnlBankDetails>
<ITRForm:BankAccounts>3</ITRForm:BankAccounts>
</ITRForm:BankAccountDtls>
</ITRForm:Refund>
<ITR4SFORM:TaxExmpIntInc>0</ITR4SFORM:TaxExmpIntInc>
<ITRForm:Verification>
<ITRForm:Declaration>
<ITRForm:AssesseeVerName>UTPAL  MONDAL</ITRForm:AssesseeVerName>
<ITRForm:FatherName>TARAPADA MONDAL</ITRForm:FatherName>
<ITRForm:AssesseeVerPAN>AOAPM7867B</ITRForm:AssesseeVerPAN>
</ITRForm:Declaration>
<ITRForm:Place>KOLKATA</ITRForm:Place>
<ITRForm:Date>2017-03-10</ITRForm:Date>
</ITRForm:Verification>
<ITRForm:NatOfBus>
<ITRForm:NatureOfBusiness>
<ITRForm:Code>0202</ITRForm:Code>
<ITRForm:TradeName1>M/S JAL KHABER AND PAPER</ITRForm:TradeName1>
</ITRForm:NatureOfBusiness>
</ITRForm:NatOfBus>
<ITRForm:ScheduleBPForITR4S>
<ITRForm:PersumptiveInc44AD>
<ITRForm:GrsTrnOverOrReceipt>3262270</ITRForm:GrsTrnOverOrReceipt> 
<ITRForm:TotPersumptiveInc44AD>352297</ITRForm:TotPersumptiveInc44AD> 
</ITRForm:PersumptiveInc44AD>
<ITRForm:PersumptiveInc44AE>
<ITRForm:TotPersumInc44AE>0</ITRForm:TotPersumInc44AE>
<ITRForm:SalInterestByFirm>0</ITRForm:SalInterestByFirm>
<ITRForm:TotalPersumptiveInc>352297</ITRForm:TotalPersumptiveInc> 
</ITRForm:PersumptiveInc44AE>
<ITRForm:IncChargeableUnderBus>352297</ITRForm:IncChargeableUnderBus>
<ITRForm:NoBooksOfAccBS>
<ITRForm:TotSundryDbtAmt>90270</ITRForm:TotSundryDbtAmt> 
<ITRForm:TotSundryCrdAmt>0</ITRForm:TotSundryCrdAmt> 
<ITRForm:TotStkInTradAmt>395270</ITRForm:TotStkInTradAmt> 
<ITRForm:CashBalAmt>228262</ITRForm:CashBalAmt> 
</ITRForm:NoBooksOfAccBS>
</ITRForm:ScheduleBPForITR4S>
<ITRForm:TotalHeavyVehcl>0</ITRForm:TotalHeavyVehcl>
<ITRForm:ScheduleAL>
<ITRForm:ImmovableAssetLand>0</ITRForm:ImmovableAssetLand>
<ITRForm:ImmovableAssetBuilding>0</ITRForm:ImmovableAssetBuilding>
<ITRForm:MovableAsset>
<ITRForm:CashInHand>0</ITRForm:CashInHand>
<ITRForm:JewelleryBullionEtc>0</ITRForm:JewelleryBullionEtc>
<ITRForm:VehiclYachtsBoatsAircrafts>0</ITRForm:VehiclYachtsBoatsAircrafts>
<ITRForm:TotalImmovablMovablAssets>0</ITRForm:TotalImmovablMovablAssets>
</ITRForm:MovableAsset>
<ITRForm:LiabilityInRelatAssets>0</ITRForm:LiabilityInRelatAssets> 
</ITRForm:ScheduleAL>
</ITR4SFORM:ITR4S>
</ITRETURN:ITR>
